[{"id":"931BEE17-EE46-47D9-BA22-36CA8CA0A934","name":"basic1","setCode":"ToSmithereens","properties":{"description":{"def":{"name":"description","type":"string","display":"Description","displayEmpty":"","displayEmptyFirst":false,"delimiter":"","backName":"","frontName":"","properties":[]},"value":""}},"isBackFaceCard":false,"backFaceId":""},{"id":"11AEF145-1DC5-4896-863D-0CB9C5C5329F","name":"system1","setCode":"ToSmithereens","properties":{"description":{"def":{"name":"description","type":"string","display":"Description","displayEmpty":"","displayEmptyFirst":false,"delimiter":"","backName":"","frontName":"","properties":[]},"value":""}},"isBackFaceCard":false,"backFaceId":""},{"id":"BFEF434B-18DB-42C0-994C-8FD681708006","name":"tactical1","setCode":"ToSmithereens","properties":{"description":{"def":{"name":"description","type":"string","display":"Description","displayEmpty":"","displayEmptyFirst":false,"delimiter":"","backName":"","frontName":"","properties":[]},"value":""}},"isBackFaceCard":false,"backFaceId":""},{"id":"13EA5D81-5556-4128-8DF9-095EF1E3ED09","name":"tech1","setCode":"ToSmithereens","properties":{"description":{"def":{"name":"description","type":"string","display":"Description","displayEmpty":"","displayEmptyFirst":false,"delimiter":"","backName":"","frontName":"","properties":[]},"value":""}},"isBackFaceCard":false,"backFaceId":""},{"id":"65A86A04-86D4-4B3D-A36A-17B7D4AABDAC","name":"countermeasures","setCode":"ToSmithereens","properties":{"description":{"def":{"name":"description","type":"string","display":"Description","displayEmpty":"","displayEmptyFirst":false,"delimiter":"","backName":"","frontName":"","properties":[]},"value":""}},"isBackFaceCard":false,"backFaceId":""},{"id":"51630512-8F31-436A-88CC-5C918AC7DAD2","name":"reactor","setCode":"ToSmithereens","properties":{"description":{"def":{"name":"description","type":"string","display":"Description","displayEmpty":"","displayEmptyFirst":false,"delimiter":"","backName":"","frontName":"","properties":[]},"value":""}},"isBackFaceCard":false,"backFaceId":""},{"id":"88A91F7B-7123-4495-90C6-F772ACAA3DBF","name":"engines","setCode":"ToSmithereens","properties":{"description":{"def":{"name":"description","type":"string","display":"Description","displayEmpty":"","displayEmptyFirst":false,"delimiter":"","backName":"","frontName":"","properties":[]},"value":""}},"isBackFaceCard":false,"backFaceId":""},{"id":"DBC3D5F3-6DD2-4A93-9592-C17A25031205","name":"weapons","setCode":"ToSmithereens","properties":{"description":{"def":{"name":"description","type":"string","display":"Description","displayEmpty":"","displayEmptyFirst":false,"delimiter":"","backName":"","frontName":"","properties":[]},"value":""}},"isBackFaceCard":false,"backFaceId":""}]